<?xml version="1.0"?>
<b:Sources SelectedStyle="" xmlns:b="http://schemas.openxmlformats.org/officeDocument/2006/bibliography" xmlns="http://schemas.openxmlformats.org/officeDocument/2006/bibliography"><b:Source><b:Year>2010</b:Year><b:BIBTEX_Entry>inbook</b:BIBTEX_Entry><b:SourceType>BookSection</b:SourceType><b:Title>Pro Asp. net 4 in C 2010</b:Title><b:Tag>macdonald2010pro</b:Tag><b:Publisher>Apress</b:Publisher><b:Author><b:Author><b:NameList><b:Person><b:Last>MacDonald</b:Last><b:First>Matthew</b:First></b:Person><b:Person><b:Last>Freeman</b:Last><b:First>Adam</b:First></b:Person></b:NameList></b:Author></b:Author><b:Pages>1397-1436</b:Pages></b:Source><b:Source><b:Year>2013</b:Year><b:Volume>30</b:Volume><b:BIBTEX_Entry>article</b:BIBTEX_Entry><b:SourceType>JournalArticle</b:SourceType><b:Title>Characterizing Architecturally Significant Requirements</b:Title><b:Tag>chen_characterizing_2013</b:Tag><b:URL>http://ieeexplore.ieee.org/lpdocs/epic03/wrapper.htm?arnumber=6365165</b:URL><b:DOI>10.1109/MS.2012.174</b:DOI><b:Author><b:Author><b:NameList><b:Person><b:Last>Chen</b:Last><b:First>Lianping</b:First></b:Person><b:Person><b:Last>Ali Babar</b:Last><b:First>Muhammad</b:First></b:Person><b:Person><b:Last>Nuseibeh</b:Last><b:First>Bashar</b:First></b:Person></b:NameList></b:Author></b:Author><b:Pages>38-45</b:Pages><b:Month>#mar#</b:Month><b:JournalName>IEEE Software</b:JournalName><b:StandardNumber> ISSN: 0740-7459</b:StandardNumber></b:Source><b:Source><b:Year>2007</b:Year><b:Volume>13</b:Volume><b:BIBTEX_Entry>article</b:BIBTEX_Entry><b:SourceType>JournalArticle</b:SourceType><b:Title>Social Network Sites: Definition, History, and Scholarship</b:Title><b:Tag>JCC4:JCC4393</b:Tag><b:Publisher>Blackwell Publishing Inc</b:Publisher><b:URL>http://dx.doi.org/10.1111/j.1083-6101.2007.00393.x</b:URL><b:DOI>10.1111/j.1083-6101.2007.00393.x</b:DOI><b:Author><b:Author><b:NameList><b:Person><b:Last>Boyd</b:Last><b:Middle>M.</b:Middle><b:First>Danah</b:First></b:Person><b:Person><b:Last>Ellison</b:Last><b:Middle>B.</b:Middle><b:First>Nicole</b:First></b:Person></b:NameList></b:Author></b:Author><b:Pages>210-230</b:Pages><b:JournalName>Journal of Computer-Mediated Communication</b:JournalName><b:StandardNumber> ISSN: 1083-6101</b:StandardNumber></b:Source><b:Source><b:Year>2007</b:Year><b:BIBTEX_Entry>inproceedings</b:BIBTEX_Entry><b:SourceType>ConferenceProceedings</b:SourceType><b:Title>Anatomy of the ado. net entity framework</b:Title><b:Tag>adya2007anatomy</b:Tag><b:BookTitle>Proceedings of the 2007 ACM SIGMOD international conference on Management of data</b:BookTitle><b:Author><b:Author><b:NameList><b:Person><b:Last>Adya</b:Last><b:First>Atul</b:First></b:Person><b:Person><b:Last>Blakeley</b:Last><b:Middle>A.</b:Middle><b:First>José</b:First></b:Person><b:Person><b:Last>Melnik</b:Last><b:First>Sergey</b:First></b:Person><b:Person><b:Last>Muralidhar</b:Last><b:First>S.</b:First></b:Person></b:NameList></b:Author></b:Author><b:Pages>877-888</b:Pages><b:ConferenceName>Proceedings of the 2007 ACM SIGMOD international conference on Management of data</b:ConferenceName></b:Source><b:Source><b:Tag>Mic14</b:Tag><b:SourceType>DocumentFromInternetSite</b:SourceType><b:Guid>{897D585C-A3D4-43FF-901E-2753055D63D2}</b:Guid><b:Author><b:Author><b:Corporate>Microsoft Corporation</b:Corporate></b:Author></b:Author><b:Title>ASP.NET Dynamic Data</b:Title><b:Year>2014</b:Year><b:InternetSiteTitle>MSDN</b:InternetSiteTitle><b:YearAccessed>2016</b:YearAccessed><b:MonthAccessed>September</b:MonthAccessed><b:DayAccessed>24</b:DayAccessed></b:Source></b:Sources>
